diff_json/__init__.py
diff_json/__version__.py
diff_json/diffing.py
diff_json/exceptions.py
diff_json/mapping.py
diff_json/op_timer.py
diff_json/pathfinding.py
diff_json/utility.py
diff_json_lr-0.0.1.dist-info/LICENSE
diff_json_lr-0.0.1.dist-info/METADATA
diff_json_lr-0.0.1.dist-info/WHEEL
diff_json_lr-0.0.1.dist-info/top_level.txt
diff_json_lr-0.0.1.dist-info/RECORD
