Metadata-Version: 2.1
Name: diff_json_lr
Version: 0.0.1
Summary: Finds differences between JSON objects to create a patch document or a left-right diff view
Author: Josh MacLachlan
Author-email: Josh MacLachlan <josh.maclachlan@equifax.com>
Project-URL: Homepage, https://github.com/jtmaclachlan/diff_json/python
Classifier: Programming Language :: Python :: 3
Classifier: License :: OSI Approved :: MIT License
Classifier: Operating System :: OS Independent
Requires-Python: >=3.10.5
License-File: LICENSE
